tatpulsar/__init__.py
tatpulsar/config.py
tatpulsar/data/__init__.py
tatpulsar/data/profile.py
tatpulsar/launcher/TATResiduals.py
tatpulsar/launcher/TATfold2d.py
tatpulsar/launcher/TATgti-generator.py
tatpulsar/pulse/__init__.py
tatpulsar/pulse/binary.py
tatpulsar/pulse/binarycor.cpython-37m-darwin.so
tatpulsar/pulse/binarycor.pyx
tatpulsar/pulse/fold.py
tatpulsar/pulse/residuals.py
tatpulsar/pulse/search.py
tatpulsar/pulse/toa.py
tatpulsar/pulse/Crab/Crab.gro
tatpulsar/pulse/Crab/__init__.py
tatpulsar/pulse/Crab/retrive_eph.py
tatpulsar/pulse/barycor/__init__.py
tatpulsar/pulse/barycor/barycor.py
tatpulsar/pulse/barycor/de200.bsp
tatpulsar/pulse/barycor/de421.bsp
tatpulsar/pulse/barycor/tdb2tdt.py
tatpulsar/utils/__init__.py
tatpulsar/utils/functions.py
tat_pulsar-0.4.2.dist-info/LICENSE
tat_pulsar-0.4.2.dist-info/METADATA
tat_pulsar-0.4.2.dist-info/WHEEL
tat_pulsar-0.4.2.dist-info/entry_points.txt
tat_pulsar-0.4.2.dist-info/top_level.txt
tat_pulsar-0.4.2.dist-info/RECORD
