Metadata-Version: 2.1
Name: tat-pulsar
Version: 0.4.2
Summary: timing library for high energy Pulsar observation
Home-page: https://github.com/tuoyl/tat-pulsar
Author: Youli Tuo
Author-email: tuoyl@ihep.ac.cn
License: MIT
Classifier: License :: OSI Approved :: MIT License
Classifier: Programming Language :: Python
Classifier: Programming Language :: Python :: 3
Classifier: Programming Language :: Python :: 3.7
Classifier: Programming Language :: Python :: Implementation :: CPython
Classifier: Programming Language :: Python :: Implementation :: PyPy
Requires-Python: >=3.7.10
License-File: LICENSE
Requires-Dist: numpy
Requires-Dist: numba
Requires-Dist: matplotlib
Requires-Dist: astropy
Requires-Dist: jplephem
Requires-Dist: scipy
Requires-Dist: pint-pulsar
Requires-Dist: SciencePlots
Requires-Dist: Cython
Requires-Dist: tk
Requires-Dist: tqdm
